{
    "Tasks": [
        {
            "taskId": 1,
            "createdTime": "Thu, 10 Sep, 2015 1356",
            "lastModifiedTime": "Thu, 10 Sep, 2015 1356",
            "startTime": "Thu, 10 Sep, 2015 1200",
            "endTime": "Fri, 11 Sep, 2015 1400",
            "deadline": "Sat, 12 Sep, 2015 1200",
            "venue": "NUS",
            "description": "Buy lunch",
            "isDone": false,
            "isPastDeadline": false,
            "hasEnded": false
        },
        {
            "taskId": 3,
            "createdTime": "Mon, 12 Oct, 2015 1641",
            "lastModifiedTime": "Mon, 12 Oct, 2015 1641",
            "startTime": null,
            "endTime": null,
            "deadline": null,
            "venue": null,
            "description": "buy lunch",
            "isDone": false,
            "isPastDeadline": true,
            "hasEnded": false
        },
        {
            "taskId": 4,
            "createdTime": "Mon, 12 Oct, 2015 1643",
            "lastModifiedTime": "Mon, 12 Oct, 2015 1643",
            "startTime": "Mon, 12 Oct, 2015 1200",
            "endTime": "Mon, 12 Oct, 2015 1300",
            "deadline": null,
            "venue": "NUS",
            "description": "buy lunch",
            "isDone": false,
            "isPastDeadline": false,
            "hasEnded": true
        },
        {
            "taskId": 5,
            "createdTime": "Mon, 12 Oct, 2015 1644",
            "lastModifiedTime": "Mon, 12 Oct, 2015 1644",
            "startTime": null,
            "endTime": null,
            "deadline": "Mon, 12 Oct, 2015 1200",
            "venue": "NUS",
            "description": "buy dinner",
            "isDone": false,
            "isPastDeadline": true,
            "hasEnded": false
        }
    ]
}